hyckle.py
hyckle-1.0.3.dist-info/LICENSE
hyckle-1.0.3.dist-info/METADATA
hyckle-1.0.3.dist-info/WHEEL
hyckle-1.0.3.dist-info/top_level.txt
hyckle-1.0.3.dist-info/RECORD
