Metadata-Version: 2.1
Name: hyckle
Version: 1.0.3
Summary: A memory-friendly warpper of pickle with better compression.
Home-page: https://github.com/zylo117/Hyckle/
Author: zylo117
Author-email: zylo117@hotmail.com
License: GPL-3.0
Platform: any
Classifier: Development Status :: 4 - Beta
Classifier: Intended Audience :: Developers
Classifier: Intended Audience :: Information Technology
Classifier: Intended Audience :: Science/Research
Classifier: License :: OSI Approved :: GNU General Public License v3 (GPLv3)
Classifier: Operating System :: OS Independent
Classifier: Programming Language :: Python
Classifier: Programming Language :: Python :: 2
Classifier: Programming Language :: Python :: 3
Classifier: Topic :: Database
Classifier: Topic :: Scientific/Engineering
Classifier: Topic :: Software Development :: Libraries :: Python Modules
